{
    "charts": [],
    "content": "[{\"id\":\"hero\",\"type\":\"hero\",\"data\":{\"heading\":\"Trustbit School Book Seller\",\"subheading\":\"Manage your school book inventory efficiently\",\"image\":\"\"}}]",
    "creation": "2024-12-25 00:00:00.000000",
    "docstatus": 0,
    "doctype": "Workspace",
    "for_user": "",
    "hide_custom": 0,
    "icon": "book",
    "idx": 0,
    "is_hidden": 0,
    "label": "School Book Seller",
    "links": [
        {
            "hidden": 0,
            "is_query_report": 0,
            "label": "Book Item Creator",
            "link_count": 0,
            "link_to": "Book Item Creator",
            "link_type": "DocType",
            "onboard": 1,
            "type": "Link"
        },
        {
            "hidden": 0,
            "is_query_report": 0,
            "label": "Publication",
            "link_count": 0,
            "link_to": "Publication",
            "link_type": "DocType",
            "onboard": 1,
            "type": "Link"
        },
        {
            "hidden": 0,
            "is_query_report": 0,
            "label": "Subject",
            "link_count": 0,
            "link_to": "Subject",
            "link_type": "DocType",
            "onboard": 0,
            "type": "Link"
        },
        {
            "hidden": 0,
            "is_query_report": 0,
            "label": "Class Master",
            "link_count": 0,
            "link_to": "Class Master",
            "link_type": "DocType",
            "onboard": 0,
            "type": "Link"
        },
        {
            "hidden": 0,
            "is_query_report": 1,
            "label": "Book Items Report",
            "link_count": 0,
            "link_to": "Book Items Report",
            "link_type": "Report",
            "onboard": 0,
            "type": "Link"
        },
        {
            "hidden": 0,
            "is_query_report": 1,
            "label": "Book Creation Summary",
            "link_count": 0,
            "link_to": "Book Creation Summary",
            "link_type": "Report",
            "onboard": 0,
            "type": "Link"
        }
    ],
    "modified": "2024-12-25 00:00:00.000000",
    "modified_by": "Administrator",
    "module": "Trustbit School Book",
    "name": "School Book Seller",
    "owner": "Administrator",
    "parent_page": "",
    "public": 1,
    "restrict_to_domain": "",
    "roles": [],
    "sequence_id": 1,
    "shortcuts": [
        {
            "color": "Green",
            "doc_view": "List",
            "label": "Book Item Creator",
            "link_to": "Book Item Creator",
            "type": "DocType"
        },
        {
            "color": "Blue",
            "doc_view": "List",
            "label": "Publications",
            "link_to": "Publication",
            "type": "DocType"
        },
        {
            "color": "Orange",
            "doc_view": "List",
            "label": "Items",
            "link_to": "Item",
            "type": "DocType"
        },
        {
            "color": "Yellow",
            "doc_view": "",
            "label": "Book Items Report",
            "link_to": "Book Items Report",
            "type": "Report"
        }
    ],
    "title": "School Book Seller"
}
